openid_redis-1.1.dist-info/DESCRIPTION.rst
openid_redis-1.1.dist-info/entry_points.txt
openid_redis-1.1.dist-info/METADATA
openid_redis-1.1.dist-info/pydist.json
openid_redis-1.1.dist-info/RECORD
openid_redis-1.1.dist-info/top_level.txt
openid_redis-1.1.dist-info/WHEEL
openidredis/__init__.py
