Metadata-Version: 2.0
Name: openid-redis
Version: 1.1
Summary: A Redis storage backend for the python-openid package
Home-page: http://github.com/bbangert/openid-redis
Author: Ben Bangert
Author-email: ben@groovie.org
License: MIT
Keywords: openid redis
Platform: UNKNOWN
Classifier: Development Status :: 6 - Mature
Classifier: Intended Audience :: Developers
Classifier: License :: OSI Approved :: MIT License
Classifier: Topic :: Internet :: WWW/HTTP
Requires-Dist: redis (>=2.4.0)
Requires-Dist: python-openid (>=2.2.5)
